LICENSE
MANIFEST.in
README.rst
setup.py
altmetric/__init__.py
altmetric/altmetric.py
altmetric.egg-info/PKG-INFO
altmetric.egg-info/SOURCES.txt
altmetric.egg-info/dependency_links.txt
altmetric.egg-info/requires.txt
altmetric.egg-info/top_level.txt
altmetric.egg-info/zip-safe