Metadata-Version: 1.1
Name: altmetric
Version: 1.0
Summary: Altmetric API v1 wrapper for Python.
Home-page: https://github.com/lnielsen-cern/python-altmetric
Author: Lars Holm Nielsen
Author-email: UNKNOWN
License: UNKNOWN
Download-URL: http://pypi.python.org/pypi/altmetric/
Keywords: altmetric api wrapper export
Platform: UNKNOWN
Classifier: Development Status :: 5 - Production/Stable
Classifier: Intended Audience :: Developers
Classifier: License :: OSI Approved :: MIT License
Classifier: Natural Language :: English
Classifier: Operating System :: OS Independent
Classifier: Programming Language :: Python
Classifier: Topic :: Software Development :: Libraries :: Python Modules
